morejpeg/__init__.py
morejpeg/main.py
morejpeg-1.1.0.dist-info/METADATA
morejpeg-1.1.0.dist-info/WHEEL
morejpeg-1.1.0.dist-info/entry_points.txt
morejpeg-1.1.0.dist-info/RECORD
